{
    "CPUGroups": [
        {
            "blendMode": "kBlendModeAdd",
            "gameMaxParticleCount_": 16,
            "name": "centerPlane",
            "phases": [
                {
                    "duration": 4.0,
                    "notEmit": false,
                    "postProcessMask_": 16649,
                    "spawn": {
                        "params": {
                            "common": {
                                "emitCount": {
                                    "constant": 4,
                                    "randomMax": 4,
                                    "randomMin": 4,
                                    "valueType": 0
                                },
                                "lifeTime": {
                                    "constant": 4.0,
                                    "randomMax": 0.800000011920929,
                                    "randomMin": 0.800000011920929,
                                    "valueType": 0
                                },
                                "moveSpeed": {
                                    "constant": 0.0,
                                    "randomMax": 1.600000023841858,
                                    "randomMin": 1.600000023841858,
                                    "valueType": 0
                                },
                                "noiseTextureName": "noise",
                                "primitive": {
                                    "plane": {
                                        "mode": "XY",
                                        "pivot": {
                                            "x": 0.5,
                                            "y": 0.5
                                        },
                                        "size": {
                                            "x": 1.0,
                                            "y": 1.0
                                        }
                                    },
                                    "shape": "Plane"
                                },
                                "samplerType": 0,
                                "textureName": "redCircle",
                                "useNoiseTexture": 0
                            },
                            "radius": 0.019999999552965164,
                            "translation": {
                                "x": 0.0,
                                "y": 0.0,
                                "z": 0.0
                            }
                        },
                        "type": "Sphere"
                    },
                    "updaters": [
                        {
                            "params": null,
                            "type": "Velocity"
                        },
                        {
                            "params": {
                                "addRotation": {
                                    "x": 0.0,
                                    "y": 0.0,
                                    "z": 0.0
                                },
                                "billboardType": "None",
                                "easingType": "EaseInSine",
                                "lerpRotation": {
                                    "start": {
                                        "x": 0.0,
                                        "y": 0.0,
                                        "z": 0.0
                                    },
                                    "target": {
                                        "x": 0.0,
                                        "y": 0.0,
                                        "z": 0.0
                                    }
                                },
                                "lockAxis": {
                                    "x": 1.5700000524520874,
                                    "y": 0.0,
                                    "z": 0.0
                                },
                                "lockAxisType": "AxisX",
                                "updateType": "Lerp"
                            },
                            "type": "Rotation"
                        },
                        {
                            "params": {
                                "color": {
                                    "start": {
                                        "a": 1.0,
                                        "b": 0.7646777629852295,
                                        "g": 0.136392742395401,
                                        "r": 0.28454282879829407
                                    },
                                    "target": {
                                        "a": 1.0,
                                        "b": 0.7646777629852295,
                                        "g": 0.136392742395401,
                                        "r": 0.28454282879829407
                                    }
                                },
                                "easingType": "EaseInSine",
                                "loop": {
                                    "loopCount": 1,
                                    "type": "Repeat"
                                }
                            },
                            "type": "Color"
                        },
                        {
                            "params": {
                                "easingType": "EaseInSine",
                                "loop": {
                                    "loopCount": 1,
                                    "type": "Repeat"
                                },
                                "scale": {
                                    "start": {
                                        "x": 64.0,
                                        "y": 64.0,
                                        "z": 32.0
                                    },
                                    "target": {
                                        "x": 64.0,
                                        "y": 64.0,
                                        "z": 32.0
                                    }
                                }
                            },
                            "type": "Scale"
                        },
                        {
                            "params": {
                                "color": {
                                    "start": {
                                        "x": 0.23499014973640442,
                                        "y": 0.08412845432758331,
                                        "z": 0.6649649143218994
                                    },
                                    "target": {
                                        "x": 0.23499014973640442,
                                        "y": 0.08412845432758331,
                                        "z": 0.6649649143218994
                                    }
                                },
                                "easingType": "EaseInSine",
                                "intencity": {
                                    "start": 0.3199999928474426,
                                    "target": 0.3199999928474426
                                }
                            },
                            "type": "Emissive"
                        }
                    ]
                }
            ],
            "primitive": "Plane",
            "textureName": ""
        }
    ],
    "name": "bossEnemyChargePlne",
    "primitiveType": "Plane"
}